{
  "name": "@srdjan/hsx-widgets",
  "version": "0.1.1",
  "exports": {
    ".": "./mod.ts",
    "./ssr": "./ssr-adapter.ts",
    "./styles": "./styles.ts"
  },
  "imports": {
    "@srdjan/hsx": "jsr:@srdjan/hsx@^1.2.0",
    "@srdjan/hsx/core": "jsr:@srdjan/hsx@^1.2.0/core",
    "@srdjan/hsx/components": "jsr:@srdjan/hsx@^1.2.0/components",
    "hsx/jsx-runtime": "jsr:@srdjan/hsx@^1.2.0/jsx-runtime"
  },
  "publish": {
    "exclude": ["build/", "examples/", "*.test.ts"]
  },
  "compilerOptions": {
    "jsx": "react-jsx",
    "jsxImportSource": "@srdjan/hsx",
    "strict": true
  }
}
